AUTHORS
Changelog
FAQ
INSTALL
LICENSE
MANIFEST.in
README
README.rst
THANKS
TODO
setup.cfg
setup.py
carrot/__init__.py
carrot/connection.py
carrot/messaging.py
carrot/serialization.py
carrot/utils.py
carrot/backends/__init__.py
carrot/backends/base.py
carrot/backends/librabbitmq.py
carrot/backends/pikachu.py
carrot/backends/pyamqplib.py
carrot/backends/pystomp.py
carrot/backends/queue.py
docs/Makefile
docs/changelog.rst
docs/conf.py
docs/faq.rst
docs/index.rst
docs/introduction.rst
docs/.static/.keep
docs/_ext/applyxrefs.py
docs/_ext/literals_to_xrefs.py
docs/_theme/agogo/layout.html
docs/_theme/agogo/theme.conf
docs/_theme/agogo/static/agogo.css_t
docs/_theme/agogo/static/bgfooter.png
docs/_theme/agogo/static/bgtop.png
docs/_theme/nature/theme.conf
docs/_theme/nature/static/nature.css_t
docs/_theme/nature/static/pygments.css
docs/reference/carrot.backends.base.rst
docs/reference/carrot.backends.librabbitmq.rst
docs/reference/carrot.backends.pikachu.rst
docs/reference/carrot.backends.pyamqplib.rst
docs/reference/carrot.backends.pystomp.rst
docs/reference/carrot.backends.queue.rst
docs/reference/carrot.backends.rst
docs/reference/carrot.connection.rst
docs/reference/carrot.messaging.rst
docs/reference/carrot.serialization.rst
docs/reference/carrot.utils.rst
docs/reference/index.rst
syseleven.carrot.egg-info/PKG-INFO
syseleven.carrot.egg-info/SOURCES.txt
syseleven.carrot.egg-info/dependency_links.txt
syseleven.carrot.egg-info/not-zip-safe
syseleven.carrot.egg-info/requires.txt
syseleven.carrot.egg-info/top_level.txt
tests/__init__.py
tests/backend.py
tests/test_django.py
tests/test_examples.py
tests/test_pyamqplib.py
tests/test_pyqueue.py
tests/test_serialization.py
tests/test_utils.py
tests/test_with_statement.py
tests/utils.py
tests/xxxstmop.py